setup.cfg
setup.py
psystem/__init__.py
psystem/errors.py
psystem/log.py
psystem/mail.py
psystem/network.py
psystem/shell.py
psystem/stats.py
psystem/system.py
psystem.egg-info/PKG-INFO
psystem.egg-info/SOURCES.txt
psystem.egg-info/dependency_links.txt
psystem.egg-info/requires.txt
psystem.egg-info/top_level.txt
test/test_network.py
test/test_shell.py
test/test_stats.py
test/test_system.py