Metadata-Version: 1.1
Name: psystem
Version: 0.2.0
Summary: Linux System Python Module
Home-page: https://github.com/gokhanm/psystem
Author: Gokhan Mankara
Author-email: gokhan@mankara.org
License: GNU GENERAL PUBLIC LICENSE
Keywords: linux system,network,mail,shell,log
Platform: UNKNOWN
Classifier: Development Status :: 5 - Production/Stable
Classifier: Intended Audience :: Developers
Classifier: Intended Audience :: System Administrators
Classifier: Programming Language :: Python
Classifier: Programming Language :: Python :: 2.7
Classifier: Programming Language :: Python :: 3.5
Classifier: License :: OSI Approved :: GNU General Public License v3 (GPLv3)
Classifier: Topic :: System :: Systems Administration
